{
  "asset_name": "built_in_double_electric_oven",
  "description": "built_in_double_electric_oven",
  "is_articulated": true,
  "body_dims": [
    0.6,
    0.5,
    0.8
  ],
  "body_material": "metal",
  "links": {
    "body": {
      "mass_kg": 40.0,
      "material": "metal",
      "is_base": true
    },
    "upper_oven_door": {
      "mass_kg": 30.0,
      "material": "metal",
      "dimensions": [
        0.6304,
        0.0943,
        0.3142
      ],
      "dimension_source": "measured",
      "is_base": false
    },
    "lower_oven_door": {
      "mass_kg": 30.0,
      "material": "metal",
      "dimensions": [
        0.6354,
        0.1468,
        0.4894
      ],
      "dimension_source": "measured",
      "is_base": false
    },
    "upper_oven_function_knob": {
      "mass_kg": 0.199,
      "material": "metal",
      "dimensions": [
        0.0435,
        0.013,
        0.0452
      ],
      "dimension_source": "measured",
      "is_base": false
    },
    "upper_oven_temperature_knob": {
      "mass_kg": 0.197,
      "material": "metal",
      "dimensions": [
        0.0422,
        0.0127,
        0.0472
      ],
      "dimension_source": "measured",
      "is_base": false
    },
    "lower_oven_function_knob": {
      "mass_kg": 0.182,
      "material": "metal",
      "dimensions": [
        0.0422,
        0.0127,
        0.0435
      ],
      "dimension_source": "measured",
      "is_base": false
    },
    "lower_oven_temperature_knob": {
      "mass_kg": 0.181,
      "material": "metal",
      "dimensions": [
        0.0422,
        0.0127,
        0.0434
      ],
      "dimension_source": "measured",
      "is_base": false
    }
  },
  "joints": {
    "upper_oven_door": {
      "type": "revolute",
      "parent": "body",
      "child": "upper_oven_door",
      "axis": "X",
      "limits": [
        -1.57,
        0
      ],
      "damping": 2.0,
      "friction": 0.1
    },
    "lower_oven_door": {
      "type": "revolute",
      "parent": "body",
      "child": "lower_oven_door",
      "axis": "X",
      "limits": [
        -1.57,
        0
      ],
      "damping": 2.0,
      "friction": 0.1
    },
    "upper_oven_function_knob": {
      "type": "revolute",
      "parent": "body",
      "child": "upper_oven_function_knob",
      "axis": "Y",
      "limits": [
        0,
        4.71
      ],
      "damping": 2.0,
      "friction": 0.1
    },
    "upper_oven_temperature_knob": {
      "type": "revolute",
      "parent": "body",
      "child": "upper_oven_temperature_knob",
      "axis": "Y",
      "limits": [
        0,
        4.71
      ],
      "damping": 2.0,
      "friction": 0.1
    },
    "lower_oven_function_knob": {
      "type": "revolute",
      "parent": "body",
      "child": "lower_oven_function_knob",
      "axis": "Y",
      "limits": [
        0,
        4.71
      ],
      "damping": 2.0,
      "friction": 0.1
    },
    "lower_oven_temperature_knob": {
      "type": "revolute",
      "parent": "body",
      "child": "lower_oven_temperature_knob",
      "axis": "Y",
      "limits": [
        0,
        4.71
      ],
      "damping": 2.0,
      "friction": 0.1
    }
  },
  "_gemini_source": {
    "object_type": "built_in_double_electric_oven",
    "parts": [
      {
        "name": "upper_oven_door",
        "type": "revolute",
        "hinge_side": "bottom",
        "interaction": {
          "type": "handle_bar",
          "orientation": "horizontal",
          "placement": "upper_third"
        },
        "material": "metal",
        "shape": {
          "base_form": "flat_panel",
          "sub_features": [
            {
              "name": "glass_window",
              "coverage_pct": 75,
              "material": "glass",
              "is_transparent": true
            }
          ]
        }
      },
      {
        "name": "lower_oven_door",
        "type": "revolute",
        "hinge_side": "bottom",
        "interaction": {
          "type": "handle_bar",
          "orientation": "horizontal",
          "placement": "upper_third"
        },
        "material": "metal",
        "shape": {
          "base_form": "flat_panel",
          "sub_features": [
            {
              "name": "glass_window",
              "coverage_pct": 75,
              "material": "glass",
              "is_transparent": true
            }
          ]
        }
      },
      {
        "name": "upper_oven_function_knob",
        "type": "revolute",
        "hinge_side": "none",
        "interaction": {
          "type": "knob",
          "orientation": "perpendicular",
          "placement": "flush"
        },
        "material": "metal",
        "shape": {
          "base_form": "cylinder",
          "sub_features": []
        }
      },
      {
        "name": "upper_oven_temperature_knob",
        "type": "revolute",
        "hinge_side": "none",
        "interaction": {
          "type": "knob",
          "orientation": "perpendicular",
          "placement": "flush"
        },
        "material": "metal",
        "shape": {
          "base_form": "cylinder",
          "sub_features": []
        }
      },
      {
        "name": "lower_oven_function_knob",
        "type": "revolute",
        "hinge_side": "none",
        "interaction": {
          "type": "knob",
          "orientation": "perpendicular",
          "placement": "flush"
        },
        "material": "metal",
        "shape": {
          "base_form": "cylinder",
          "sub_features": []
        }
      },
      {
        "name": "lower_oven_temperature_knob",
        "type": "revolute",
        "hinge_side": "none",
        "interaction": {
          "type": "knob",
          "orientation": "perpendicular",
          "placement": "flush"
        },
        "material": "metal",
        "shape": {
          "base_form": "cylinder",
          "sub_features": []
        }
      }
    ],
    "visual_only_parts": [
      {
        "name": "digital_clock_display",
        "what_it_is": "digital_display",
        "location": "center_of_top_control_panel"
      },
      {
        "name": "Aduro_brand_logo",
        "what_it_is": "brand_logo",
        "location": "bottom_center_of_lower_oven_door_frame"
      }
    ],
    "front_face_layout": [
      {
        "name": "top_control_panel",
        "height_pct": 12,
        "description": "Contains four control knobs and a digital display for time/settings."
      },
      {
        "name": "upper_oven_section",
        "height_pct": 42,
        "description": "The upper oven compartment with a glass viewing window and horizontal handle."
      },
      {
        "name": "middle_divider_panel",
        "height_pct": 2,
        "description": "A thin horizontal metal strip separating the two oven compartments."
      },
      {
        "name": "lower_oven_section",
        "height_pct": 42,
        "description": "The lower oven compartment with a glass viewing window, horizontal handle, and brand logo."
      },
      {
        "name": "bottom_trim_panel",
        "height_pct": 2,
        "description": "A thin horizontal metal strip at the very bottom of the appliance."
      }
    ],
    "count_summary": {
      "doors": 2,
      "knobs": 4,
      "handles": 2,
      "buttons": 0,
      "digital_displays": 1
    }
  }
}